README.md
setup.cfg
setup.py
sagecipher/__init__.py
sagecipher/__main__.py
sagecipher/cipher.py
sagecipher/keyring.py
sagecipher.egg-info/PKG-INFO
sagecipher.egg-info/SOURCES.txt
sagecipher.egg-info/dependency_links.txt
sagecipher.egg-info/entry_points.txt
sagecipher.egg-info/requires.txt
sagecipher.egg-info/top_level.txt
sagecipher.egg-info/zip-safe