Metadata-Version: 2.1
Name: sagecipher
Version: 0.7.3
Summary: Uses SSH agent to encrypt/decrypt arbitrary data
Home-page: https://github.com/p-sherratt/sagecipher
Author: Paul Sherratt
Author-email: paul@paul.sh
License: Apache
Keywords: ssh-agent paramiko cipher cloginrc encryption keyring ansible vault
Platform: UNKNOWN
Classifier: Development Status :: 3 - Alpha
Classifier: Intended Audience :: System Administrators
Classifier: Intended Audience :: Telecommunications Industry
Classifier: Topic :: Security :: Cryptography
Classifier: Topic :: System :: Systems Administration
Classifier: License :: OSI Approved :: Apache Software License
Classifier: Programming Language :: Python :: 3.6
Classifier: Programming Language :: Python :: 3 :: Only
